<annotation>
	<folder>wikiart</folder>
	<filename>brauner-2.jpg</filename>
	<path>/sb-personal/mafc-100/wikiart/brauner-2.jpg</path>
	<source>
		<database>Unknown</database>
	</source>
	<size>
		<width>400</width>
		<height>292</height>
		<depth>3</depth>
	</size>
	<segmented>0</segmented>
	<object>
		<name>face</name>
		<pose>Unspecified</pose>
		<truncated>0</truncated>
		<difficult>0</difficult>
		<bndbox>
			<xmin>178</xmin>
			<ymin>73</ymin>
			<xmax>258</xmax>
			<ymax>157</ymax>
		</bndbox>
	</object>
	<object>
		<name>face</name>
		<pose>Unspecified</pose>
		<truncated>0</truncated>
		<difficult>0</difficult>
		<bndbox>
			<xmin>87</xmin>
			<ymin>18</ymin>
			<xmax>163</xmax>
			<ymax>132</ymax>
		</bndbox>
	</object>
</annotation>
